setup.cfg
setup.py
cp_es.egg-info/PKG-INFO
cp_es.egg-info/SOURCES.txt
cp_es.egg-info/dependency_links.txt
cp_es.egg-info/entry_points.txt
cp_es.egg-info/not-zip-safe
cp_es.egg-info/requires.txt
cp_es.egg-info/top_level.txt
cpes/__init__.py
cpes/es_handler.py