Metadata-Version: 1.0
Name: cp-es
Version: 0.0.2
Summary: this is Carpool Project psubpackage: cp-es
Home-page: https://www.m.general.gitsite.net
Author: petergra
Author-email: lvpet@esquel.com
License: MIT
Platform: UNKNOWN
